LICENSE
MANIFEST.in
README.md
setup.py
PPP/__init__.py
PPP/adjustments_module.py
PPP/checks_module.py
PPP/constraints.py
PPP/coordinates_module.py
PPP/global_processes.py
PPP/global_variables.py
PPP/hydrogens_addition.py
PPP/main.py
PPP/mutate_PELE.py
PPP/mutational_module.py
PPP/parameters_help.py
PPP/program_own_classes.py
PPP/read_force_field_parameters.py
PPP/substructure_search.py
PPP/Data/RotamerLibs/ARG.side
PPP/Data/RotamerLibs/ASH.side
PPP/Data/RotamerLibs/ASN.side
PPP/Data/RotamerLibs/ASP.side
PPP/Data/RotamerLibs/ASQ.side
PPP/Data/RotamerLibs/BMT.side
PPP/Data/RotamerLibs/CISTRANS.side
PPP/Data/RotamerLibs/CYS.side
PPP/Data/RotamerLibs/CYX.side
PPP/Data/RotamerLibs/DAR.side
PPP/Data/RotamerLibs/DAS.side
PPP/Data/RotamerLibs/DCY.side
PPP/Data/RotamerLibs/DGE.back
PPP/Data/RotamerLibs/DGL.side
PPP/Data/RotamerLibs/DHI.side
PPP/Data/RotamerLibs/DIL.side
PPP/Data/RotamerLibs/DLE.side
PPP/Data/RotamerLibs/DLY.side
PPP/Data/RotamerLibs/DME.side
PPP/Data/RotamerLibs/DNM.back
PPP/Data/RotamerLibs/DPH.side
PPP/Data/RotamerLibs/DPR.back
PPP/Data/RotamerLibs/DPR.side
PPP/Data/RotamerLibs/DTH.side
PPP/Data/RotamerLibs/DTR.side
PPP/Data/RotamerLibs/DTY.side
PPP/Data/RotamerLibs/DVA.side
PPP/Data/RotamerLibs/FRE120.side
PPP/Data/RotamerLibs/FRE180.side
PPP/Data/RotamerLibs/FREE10.side
PPP/Data/RotamerLibs/FREE15.side
PPP/Data/RotamerLibs/FREE20.side
PPP/Data/RotamerLibs/FREE30.side
PPP/Data/RotamerLibs/FREE40.side
PPP/Data/RotamerLibs/FREE45.side
PPP/Data/RotamerLibs/FREE60.side
PPP/Data/RotamerLibs/FREE90.side
PPP/Data/RotamerLibs/FREE_5.side
PPP/Data/RotamerLibs/GEN.back
PPP/Data/RotamerLibs/GLH.side
PPP/Data/RotamerLibs/GLN.side
PPP/Data/RotamerLibs/GLU.side
PPP/Data/RotamerLibs/GLY.back
PPP/Data/RotamerLibs/HIS.side
PPP/Data/RotamerLibs/ILE.side
PPP/Data/RotamerLibs/LEU.side
PPP/Data/RotamerLibs/LYS.side
PPP/Data/RotamerLibs/MET.side
PPP/Data/RotamerLibs/NME.back
PPP/Data/RotamerLibs/OMY.side
PPP/Data/RotamerLibs/PHE.side
PPP/Data/RotamerLibs/PRO.back
PPPele.egg-info/PKG-INFO
PPPele.egg-info/SOURCES.txt
PPPele.egg-info/dependency_links.txt
PPPele.egg-info/requires.txt
PPPele.egg-info/top_level.txt