Metadata-Version: 2.1
Name: PPPele
Version: 1.0.10
Summary: Protein PELE preparation
Home-page: https://github.com/NostrumBioDiscovery/PPP
Author: Nostrum Biodiscovery
Author-email: it@nostrumbiodiscovery.com
License: UNKNOWN
Platform: UNKNOWN
License-File: LICENSE
